setup.py
drf_nested_serializers.egg-info/PKG-INFO
drf_nested_serializers.egg-info/SOURCES.txt
drf_nested_serializers.egg-info/dependency_links.txt
drf_nested_serializers.egg-info/requires.txt
drf_nested_serializers.egg-info/top_level.txt
nested_serializers/__init__.py
nested_serializers/fields.py
nested_serializers/serializers.py
nested_serializers/validators.py