Metadata-Version: 1.0
Name: drf-nested-serializers
Version: 1.0.2
Summary: America's Finest Namespace
Home-page: https://github.com/theonion/drf-nested-serializers
Author: Onion Devs
Author-email: webtech@theonion.com
License: BSD
Platform: UNKNOWN
